{"tw": {"2465840": {"success": true, "data": {"type": "game", "name": "Club Velvet Rose: Midnight Bliss", "steam_appid": 2465840, "required_age": 0, "is_free": false, "controller_support": "full", "detailed_description": "<span class=\"bb_img_ctn\"><img class=\"bb_img\" src=\"https://shared.akamai.steamstatic.com/store_item_assets/steam/apps/2465840/extras/9e82f053d68682c0f3898ec1a1aab5e5.avif?t=1747380454\" width=616 height=896 /></span><span class=\"bb_img_ctn\"><img class=\"bb_img\" src=\"https://shared.akamai.steamstatic.com/store_item_assets/steam/apps/2465840/extras/079f696cc1261f07a923211bdfcb5edb.avif?t=1747380454\" width=616 height=628 /></span><span class=\"bb_img_ctn\"><img class=\"bb_img\" src=\"https://shared.akamai.steamstatic.com/store_item_assets/steam/apps/2465840/extras/c5d5fa34169660f68d397c6e145ecea6.avif?t=1747380454\" width=616 height=762 /></span><span class=\"bb_img_ctn\"><img class=\"bb_img\" src=\"https://shared.akamai.steamstatic.com/store_item_assets/steam/apps/2465840/extras/6e30893f2477342d756a19d5837e47fb.avif?t=1747380454\" width=616 height=690 /></span><span class=\"bb_img_ctn\"><img class=\"bb_img\" src=\"https://shared.akamai.steamstatic.com/store_item_assets/steam/apps/2465840/extras/e9962ba2e1124c097a14d75a601e184e.avif?t=1747380454\" width=616 height=974 /></span>", "about_the_game": "<span class=\"bb_img_ctn\"><img class=\"bb_img\" src=\"https://shared.akamai.steamstatic.com/store_item_assets/steam/apps/2465840/extras/9e82f053d68682c0f3898ec1a1aab5e5.avif?t=1747380454\" width=616 height=896 /></span><span class=\"bb_img_ctn\"><img class=\"bb_img\" src=\"https://shared.akamai.steamstatic.com/store_item_assets/steam/apps/2465840/extras/079f696cc1261f07a923211bdfcb5edb.avif?t=1747380454\" width=616 height=628 /></span><span class=\"bb_img_ctn\"><img class=\"bb_img\" src=\"https://shared.akamai.steamstatic.com/store_item_assets/steam/apps/2465840/extras/c5d5fa34169660f68d397c6e145ecea6.avif?t=1747380454\" width=616 height=762 /></span><span class=\"bb_img_ctn\"><img class=\"bb_img\" src=\"https://shared.akamai.steamstatic.com/store_item_assets/steam/apps/2465840/extras/6e30893f2477342d756a19d5837e47fb.avif?t=1747380454\" width=616 height=690 /></span><span class=\"bb_img_ctn\"><img class=\"bb_img\" src=\"https://shared.akamai.steamstatic.com/store_item_assets/steam/apps/2465840/extras/e9962ba2e1124c097a14d75a601e184e.avif?t=1747380454\" width=616 height=974 /></span>", "short_description": "Indulge in Club Velvet Rose, an adult visual novel exploring the world of a sophisticated swingers club. Embrace desires, encounter intriguing characters, and dive into a world of passion. Expect stunning animations, inspiring dialogue, and captivating situations. Let the journey begin.", "supported_languages": "英文", "header_image": "https://shared.akamai.steamstatic.com/store_item_assets/steam/apps/2465840/header.jpg?t=1747380454", "capsule_image": "https://shared.akamai.steamstatic.com/store_item_assets/steam/apps/2465840/c1cdfae9ca958531e3487e5a7255e3fd02d8c0ea/capsule_231x87.jpg?t=1747380454", "capsule_imagev5": "https://shared.akamai.steamstatic.com/store_item_assets/steam/apps/2465840/c1cdfae9ca958531e3487e5a7255e3fd02d8c0ea/capsule_184x69.jpg?t=1747380454", "website": null, "pc_requirements": {"minimum": "<strong>最低配備:</strong><br><ul class=\"bb_ul\"><li><strong>作業系統:</strong> Windows 10<br></li><li><strong>處理器:</strong> 2.0 Ghz+<br></li><li><strong>記憶體:</strong> 4 GB 記憶體<br></li><li><strong>儲存空間:</strong> 3 GB 可用空間</li></ul>", "recommended": "<strong>建議配備:</strong><br><ul class=\"bb_ul\"><li><strong>作業系統:</strong> Windows 10<br></li><li><strong>處理器:</strong> 2.0 Ghz+<br></li><li><strong>記憶體:</strong> 4 GB 記憶體<br></li><li><strong>儲存空間:</strong> 3 GB 可用空間</li></ul>"}, "mac_requirements": {"minimum": "<strong>最低配備:</strong><br><ul class=\"bb_ul\"><li><strong>作業系統:</strong> Latest version<br></li><li><strong>處理器:</strong> 2.0 Ghz+ or M1<br></li><li><strong>記憶體:</strong> 4 GB 記憶體<br></li><li><strong>儲存空間:</strong> 3 GB 可用空間</li></ul>", "recommended": "<strong>建議配備:</strong><br><ul class=\"bb_ul\"><li><strong>作業系統:</strong> Latest version<br></li><li><strong>處理器:</strong> 2.0 Ghz+ or M1<br></li><li><strong>記憶體:</strong> 4 GB 記憶體<br></li><li><strong>儲存空間:</strong> 3 GB 可用空間</li></ul>"}, "linux_requirements": {"minimum": "<strong>最低配備:</strong><br><ul class=\"bb_ul\"><li><strong>作業系統:</strong> Latest version<br></li><li><strong>處理器:</strong> 2.0 Ghz+<br></li><li><strong>記憶體:</strong> 4 GB 記憶體<br></li><li><strong>儲存空間:</strong> 3 GB 可用空間</li></ul>", "recommended": "<strong>建議配備:</strong><br><ul class=\"bb_ul\"><li><strong>作業系統:</strong> Latest version<br></li><li><strong>處理器:</strong> 2.0 Ghz+<br></li><li><strong>記憶體:</strong> 4 GB 記憶體<br></li><li><strong>儲存空間:</strong> 3 GB 可用空間</li></ul>"}, "developers": ["Lesson of Passion"], "publishers": ["Lesson of Passion"], "price_overview": {"currency": "TWD", "initial": 18800, "final": 18800, "discount_percent": 0, "initial_formatted": "", "final_formatted": "NT$ 188"}, "categories": [{"id": 2, "description": "單人"}, {"id": 22, "description": "Steam 成就"}, {"id": 28, "description": "完全支援控制器"}, {"id": 23, "description": "Steam 雲端"}, {"id": 62, "description": "親友同享"}], "genres": [{"id": "25", "description": "冒險"}, {"id": "23", "description": "獨立製作"}], "release_date": {"coming_soon": false, "date": "2025 年 5 月 16 日"}}}}, "us": {"2465840": {"success": true, "data": {"type": "game", "name": "Club Velvet Rose: Midnight Bliss", "steam_appid": 2465840, "required_age": 0, "is_free": false, "controller_support": "full", "detailed_description": "<span class=\"bb_img_ctn\"><img class=\"bb_img\" src=\"https://shared.akamai.steamstatic.com/store_item_assets/steam/apps/2465840/extras/9e82f053d68682c0f3898ec1a1aab5e5.avif?t=1747380454\" width=616 height=896 /></span><span class=\"bb_img_ctn\"><img class=\"bb_img\" src=\"https://shared.akamai.steamstatic.com/store_item_assets/steam/apps/2465840/extras/079f696cc1261f07a923211bdfcb5edb.avif?t=1747380454\" width=616 height=628 /></span><span class=\"bb_img_ctn\"><img class=\"bb_img\" src=\"https://shared.akamai.steamstatic.com/store_item_assets/steam/apps/2465840/extras/c5d5fa34169660f68d397c6e145ecea6.avif?t=1747380454\" width=616 height=762 /></span><span class=\"bb_img_ctn\"><img class=\"bb_img\" src=\"https://shared.akamai.steamstatic.com/store_item_assets/steam/apps/2465840/extras/6e30893f2477342d756a19d5837e47fb.avif?t=1747380454\" width=616 height=690 /></span><span class=\"bb_img_ctn\"><img class=\"bb_img\" src=\"https://shared.akamai.steamstatic.com/store_item_assets/steam/apps/2465840/extras/e9962ba2e1124c097a14d75a601e184e.avif?t=1747380454\" width=616 height=974 /></span>", "about_the_game": "<span class=\"bb_img_ctn\"><img class=\"bb_img\" src=\"https://shared.akamai.steamstatic.com/store_item_assets/steam/apps/2465840/extras/9e82f053d68682c0f3898ec1a1aab5e5.avif?t=1747380454\" width=616 height=896 /></span><span class=\"bb_img_ctn\"><img class=\"bb_img\" src=\"https://shared.akamai.steamstatic.com/store_item_assets/steam/apps/2465840/extras/079f696cc1261f07a923211bdfcb5edb.avif?t=1747380454\" width=616 height=628 /></span><span class=\"bb_img_ctn\"><img class=\"bb_img\" src=\"https://shared.akamai.steamstatic.com/store_item_assets/steam/apps/2465840/extras/c5d5fa34169660f68d397c6e145ecea6.avif?t=1747380454\" width=616 height=762 /></span><span class=\"bb_img_ctn\"><img class=\"bb_img\" src=\"https://shared.akamai.steamstatic.com/store_item_assets/steam/apps/2465840/extras/6e30893f2477342d756a19d5837e47fb.avif?t=1747380454\" width=616 height=690 /></span><span class=\"bb_img_ctn\"><img class=\"bb_img\" src=\"https://shared.akamai.steamstatic.com/store_item_assets/steam/apps/2465840/extras/e9962ba2e1124c097a14d75a601e184e.avif?t=1747380454\" width=616 height=974 /></span>", "short_description": "Indulge in Club Velvet Rose, an adult visual novel exploring the world of a sophisticated swingers club. Embrace desires, encounter intriguing characters, and dive into a world of passion. Expect stunning animations, inspiring dialogue, and captivating situations. Let the journey begin.", "supported_languages": "English", "header_image": "https://shared.akamai.steamstatic.com/store_item_assets/steam/apps/2465840/header.jpg?t=1747380454", "capsule_image": "https://shared.akamai.steamstatic.com/store_item_assets/steam/apps/2465840/c1cdfae9ca958531e3487e5a7255e3fd02d8c0ea/capsule_231x87.jpg?t=1747380454", "capsule_imagev5": "https://shared.akamai.steamstatic.com/store_item_assets/steam/apps/2465840/c1cdfae9ca958531e3487e5a7255e3fd02d8c0ea/capsule_184x69.jpg?t=1747380454", "website": null, "pc_requirements": {"minimum": "<strong>Minimum:</strong><br><ul class=\"bb_ul\"><li><strong>OS:</strong> Windows 10<br></li><li><strong>Processor:</strong> 2.0 Ghz+<br></li><li><strong>Memory:</strong> 4 GB RAM<br></li><li><strong>Storage:</strong> 3 GB available space</li></ul>", "recommended": "<strong>Recommended:</strong><br><ul class=\"bb_ul\"><li><strong>OS:</strong> Windows 10<br></li><li><strong>Processor:</strong> 2.0 Ghz+<br></li><li><strong>Memory:</strong> 4 GB RAM<br></li><li><strong>Storage:</strong> 3 GB available space</li></ul>"}, "mac_requirements": {"minimum": "<strong>Minimum:</strong><br><ul class=\"bb_ul\"><li><strong>OS:</strong> Latest version<br></li><li><strong>Processor:</strong> 2.0 Ghz+ or M1<br></li><li><strong>Memory:</strong> 4 GB RAM<br></li><li><strong>Storage:</strong> 3 GB available space</li></ul>", "recommended": "<strong>Recommended:</strong><br><ul class=\"bb_ul\"><li><strong>OS:</strong> Latest version<br></li><li><strong>Processor:</strong> 2.0 Ghz+ or M1<br></li><li><strong>Memory:</strong> 4 GB RAM<br></li><li><strong>Storage:</strong> 3 GB available space</li></ul>"}, "linux_requirements": {"minimum": "<strong>Minimum:</strong><br><ul class=\"bb_ul\"><li><strong>OS:</strong> Latest version<br></li><li><strong>Processor:</strong> 2.0 Ghz+<br></li><li><strong>Memory:</strong> 4 GB RAM<br></li><li><strong>Storage:</strong> 3 GB available space</li></ul>", "recommended": "<strong>Recommended:</strong><br><ul class=\"bb_ul\"><li><strong>OS:</strong> Latest version<br></li><li><strong>Processor:</strong> 2.0 Ghz+<br></li><li><strong>Memory:</strong> 4 GB RAM<br></li><li><strong>Storage:</strong> 3 GB available space</li></ul>"}, "developers": ["Lesson of Passion"], "publishers": ["Lesson of Passion"], "price_overview": {"currency": "USD", "initial": 999, "final": 999, "discount_percent": 0, "initial_formatted": "", "final_formatted": "$9.99"}, "categories": [{"id": 2, "description": "Single-player"}, {"id": 22, "description": "Steam Achievements"}, {"id": 28, "description": "Full controller support"}, {"id": 23, "description": "Steam Cloud"}, {"id": 62, "description": "Family Sharing"}], "genres": [{"id": "25", "description": "Adventure"}, {"id": "23", "description": "Indie"}], "release_date": {"coming_soon": false, "date": "May 16, 2025"}}}}, "fetched_at": "2026-04-23T07:44:03Z"}