{"tw": {"2761510": {"success": true, "data": {"type": "game", "name": "颯爽的我與100個女友!", "steam_appid": 2761510, "required_age": 0, "is_free": false, "detailed_description": "<h1>更新計劃</h1><p><span class=\"bb_img_ctn\"><img class=\"bb_img\" src=\"https://shared.akamai.steamstatic.com/store_item_assets/steam/apps/2761510/extras/fc3527d49d133c602b2a4e3b9924e39e.avif?t=1750171410\" width=620 height=1066 /></span></p><br><h1>關於此遊戲</h1><p class=\"bb_paragraph\" ><span class=\"bb_img_ctn\"><img class=\"bb_img\" src=\"https://shared.akamai.steamstatic.com/store_item_assets/steam/apps/2761510/extras/11047887cf1268f4746045a8e0661781.avif?t=1750171410\" width=616 height=71 /></span></p><h2 class=\"bb_tag\" ><strong> <br>官方5群：974466252（已满）</strong></h2><h2 class=\"bb_tag\" ><strong>官方6群：</strong>882507347<strong>（新）</strong></h2><h2 class=\"bb_tag\" >加入社區</h2><p class=\"bb_paragraph\" ><strong>加入我們的Discord頻道：</strong></p><p class=\"bb_paragraph\" ></p><p class=\"bb_paragraph\" ><span class=\"bb_img_ctn\"><img class=\"bb_img\" src=\"https://shared.akamai.steamstatic.com/store_item_assets/steam/apps/2761510/extras/6961711820f6cd63127f0419c4791162.avif?t=1750171410\" width=640 height=64 /></span><strong>HI，我們是Philosophy♂！</strong></p><p class=\"bb_paragraph\" >這款遊戲是承載我們夢想的一款遊戲，我們希望可以製作一款簡單又自由的世界遊戲。</p><p class=\"bb_paragraph\" >你可以在世界中隨便溜達，無論是主角，還是路人，都可以隨意攻略。</p><p class=\"bb_paragraph\" ><span class=\"bb_img_ctn\"><img class=\"bb_img\" src=\"https://shared.akamai.steamstatic.com/store_item_assets/steam/apps/2761510/extras/1b76b3ea30141a8fc4eb7ac6dee4ff3d.avif?t=1750171410\" width=640 height=64 /></span>主角為平凡的家裡蹲少年，但是擁有超凡的足道技術，一面打工賺取零用錢，一面與阿姨和姐姐在同一個屋簷下生活。</p><p class=\"bb_paragraph\" ><span class=\"bb_img_ctn\"><img class=\"bb_img\" src=\"https://shared.akamai.steamstatic.com/store_item_assets/steam/apps/2761510/extras/44b44b3fcc49af03faf328b6cd44c856.avif?t=1750171410\" width=640 height=64 /></span><span class=\"bb_img_ctn\"><img class=\"bb_img\" src=\"https://shared.akamai.steamstatic.com/store_item_assets/steam/apps/2761510/extras/13ee59f71dfa8b34f0a895f4bf99ea56.avif?t=1750171410\" width=640 height=360 /></span><span class=\"bb_img_ctn\"><img class=\"bb_img\" src=\"https://shared.akamai.steamstatic.com/store_item_assets/steam/apps/2761510/extras/df3311b77c0261dc8975e4012e0a7c06.avif?t=1750171410\" width=640 height=360 /></span><span class=\"bb_img_ctn\"><img class=\"bb_img\" src=\"https://shared.akamai.steamstatic.com/store_item_assets/steam/apps/2761510/extras/010f818b80be0e4e730caaf89af2bb81.avif?t=1750171410\" width=640 height=64 /></span>● 地圖自由探索，每個建築都有自己的功能，自宅，足道店，酒店，便利商店</p><p class=\"bb_paragraph\" ><span class=\"bb_img_ctn\"><img class=\"bb_img\" src=\"https://shared.akamai.steamstatic.com/store_item_assets/steam/apps/2761510/extras/5e8926959e72b44e39df18f5cf71159a.avif?t=1750171410\" width=640 height=360 /></span>● 提升好感，讓女性從陌生，到墮落，自己當男優，所有妹子都可以錄AV分享賺錢</p><p class=\"bb_paragraph\" ><span class=\"bb_img_ctn\"><img class=\"bb_img\" src=\"https://shared.akamai.steamstatic.com/store_item_assets/steam/apps/2761510/extras/d0ebe87d037736dfb9009ede6140780e.avif?t=1750171410\" width=640 height=360 /></span></p>", "about_the_game": "<p class=\"bb_paragraph\" ><span class=\"bb_img_ctn\"><img class=\"bb_img\" src=\"https://shared.akamai.steamstatic.com/store_item_assets/steam/apps/2761510/extras/11047887cf1268f4746045a8e0661781.avif?t=1750171410\" width=616 height=71 /></span></p><h2 class=\"bb_tag\" ><strong> <br>官方5群：974466252（已满）</strong></h2><h2 class=\"bb_tag\" ><strong>官方6群：</strong>882507347<strong>（新）</strong></h2><h2 class=\"bb_tag\" >加入社區</h2><p class=\"bb_paragraph\" ><strong>加入我們的Discord頻道：</strong></p><p class=\"bb_paragraph\" ></p><p class=\"bb_paragraph\" ><span class=\"bb_img_ctn\"><img class=\"bb_img\" src=\"https://shared.akamai.steamstatic.com/store_item_assets/steam/apps/2761510/extras/6961711820f6cd63127f0419c4791162.avif?t=1750171410\" width=640 height=64 /></span><strong>HI，我們是Philosophy♂！</strong></p><p class=\"bb_paragraph\" >這款遊戲是承載我們夢想的一款遊戲，我們希望可以製作一款簡單又自由的世界遊戲。</p><p class=\"bb_paragraph\" >你可以在世界中隨便溜達，無論是主角，還是路人，都可以隨意攻略。</p><p class=\"bb_paragraph\" ><span class=\"bb_img_ctn\"><img class=\"bb_img\" src=\"https://shared.akamai.steamstatic.com/store_item_assets/steam/apps/2761510/extras/1b76b3ea30141a8fc4eb7ac6dee4ff3d.avif?t=1750171410\" width=640 height=64 /></span>主角為平凡的家裡蹲少年，但是擁有超凡的足道技術，一面打工賺取零用錢，一面與阿姨和姐姐在同一個屋簷下生活。</p><p class=\"bb_paragraph\" ><span class=\"bb_img_ctn\"><img class=\"bb_img\" src=\"https://shared.akamai.steamstatic.com/store_item_assets/steam/apps/2761510/extras/44b44b3fcc49af03faf328b6cd44c856.avif?t=1750171410\" width=640 height=64 /></span><span class=\"bb_img_ctn\"><img class=\"bb_img\" src=\"https://shared.akamai.steamstatic.com/store_item_assets/steam/apps/2761510/extras/13ee59f71dfa8b34f0a895f4bf99ea56.avif?t=1750171410\" width=640 height=360 /></span><span class=\"bb_img_ctn\"><img class=\"bb_img\" src=\"https://shared.akamai.steamstatic.com/store_item_assets/steam/apps/2761510/extras/df3311b77c0261dc8975e4012e0a7c06.avif?t=1750171410\" width=640 height=360 /></span><span class=\"bb_img_ctn\"><img class=\"bb_img\" src=\"https://shared.akamai.steamstatic.com/store_item_assets/steam/apps/2761510/extras/010f818b80be0e4e730caaf89af2bb81.avif?t=1750171410\" width=640 height=64 /></span>● 地圖自由探索，每個建築都有自己的功能，自宅，足道店，酒店，便利商店</p><p class=\"bb_paragraph\" ><span class=\"bb_img_ctn\"><img class=\"bb_img\" src=\"https://shared.akamai.steamstatic.com/store_item_assets/steam/apps/2761510/extras/5e8926959e72b44e39df18f5cf71159a.avif?t=1750171410\" width=640 height=360 /></span>● 提升好感，讓女性從陌生，到墮落，自己當男優，所有妹子都可以錄AV分享賺錢</p><p class=\"bb_paragraph\" ><span class=\"bb_img_ctn\"><img class=\"bb_img\" src=\"https://shared.akamai.steamstatic.com/store_item_assets/steam/apps/2761510/extras/d0ebe87d037736dfb9009ede6140780e.avif?t=1750171410\" width=640 height=360 /></span></p>", "short_description": "我靠著吃苦耐勞的性格開始了打工生涯，靠賺錢購買禮物贈送喜歡的角色。", "supported_languages": "英文, 日文, 簡體中文, 繁體中文", "header_image": "https://shared.akamai.steamstatic.com/store_item_assets/steam/apps/2761510/header_tchinese.jpg?t=1750171410", "capsule_image": "https://shared.akamai.steamstatic.com/store_item_assets/steam/apps/2761510/capsule_231x87_tchinese.jpg?t=1750171410", "capsule_imagev5": "https://shared.akamai.steamstatic.com/store_item_assets/steam/apps/2761510/capsule_184x69_tchinese.jpg?t=1750171410", "website": null, "pc_requirements": {"minimum": "<strong>最低配備:</strong><br><ul class=\"bb_ul\"><li><strong>作業系統 *:</strong> Windows 7<br></li><li><strong>處理器:</strong> 2 Ghz Dual Core<br></li><li><strong>記憶體:</strong> 2 GB 記憶體<br></li><li><strong>顯示卡:</strong> Graphics card supporting DirectX 10.0<br></li><li><strong>儲存空間:</strong> 4 GB 可用空間</li></ul>", "recommended": "<strong>建議配備:</strong><br><ul class=\"bb_ul\"><li><strong>作業系統:</strong> Windows 10<br></li><li><strong>記憶體:</strong> 2 GB 記憶體</li></ul>"}, "mac_requirements": [], "linux_requirements": [], "developers": ["philosophy♂"], "publishers": ["monster home"], "price_overview": {"currency": "TWD", "initial": 18800, "final": 18800, "discount_percent": 0, "initial_formatted": "", "final_formatted": "NT$ 188"}, "categories": [{"id": 2, "description": "單人"}, {"id": 62, "description": "親友同享"}], "genres": [{"id": "1", "description": "動作"}, {"id": "4", "description": "休閒"}, {"id": "23", "description": "獨立製作"}, {"id": "3", "description": "角色扮演"}, {"id": "28", "description": "模擬"}], "release_date": {"coming_soon": false, "date": "2024 年 4 月 11 日"}}}}, "us": {"2761510": {"success": true, "data": {"type": "game", "name": "Handsome Me with 100 Girlfriends!", "steam_appid": 2761510, "required_age": 0, "is_free": false, "detailed_description": "<h2 class=\"bb_tag\" >Official Community</h2><strong>Join our Discord channel：</strong><br><br><span class=\"bb_img_ctn\"><img class=\"bb_img\" src=\"https://shared.akamai.steamstatic.com/store_item_assets/steam/apps/2761510/extras/723612e7a8783ea223b3b2b5c60dbf0b.avif?t=1750171410\" width=640 height=64 /></span><br><strong>HI, we are Philosophy♂!</strong><br>This is a game that carries our dream of making a simple yet free world-based game.<br>You can just slip in and out of the world, either as a protagonist, or a passerby, and raid at will.<br><span class=\"bb_img_ctn\"><img class=\"bb_img\" src=\"https://shared.akamai.steamstatic.com/store_item_assets/steam/apps/2761510/extras/4e5b51aa912c89179168972429d2f4f1.avif?t=1750171410\" width=640 height=64 /></span><br>The protagonist is an ordinary teenager who is a squatter, but has extraordinary footwork skills, and works part-time to earn pocket money while living under the same roof as his aunt and sister.<br><span class=\"bb_img_ctn\"><img class=\"bb_img\" src=\"https://shared.akamai.steamstatic.com/store_item_assets/steam/apps/2761510/extras/ba69b27f4a3ac73673974c77ae1faa85.avif?t=1750171410\" width=640 height=64 /></span><br><span class=\"bb_img_ctn\"><img class=\"bb_img\" src=\"https://shared.akamai.steamstatic.com/store_item_assets/steam/apps/2761510/extras/13ee59f71dfa8b34f0a895f4bf99ea56.avif?t=1750171410\" width=640 height=360 /></span><br><span class=\"bb_img_ctn\"><img class=\"bb_img\" src=\"https://shared.akamai.steamstatic.com/store_item_assets/steam/apps/2761510/extras/df3311b77c0261dc8975e4012e0a7c06.avif?t=1750171410\" width=640 height=360 /></span><br><span class=\"bb_img_ctn\"><img class=\"bb_img\" src=\"https://shared.akamai.steamstatic.com/store_item_assets/steam/apps/2761510/extras/c806a4c47fffaeae792e169a1b812011.avif?t=1750171410\" width=640 height=64 /></span><br>● The map is free to explore, each building has its own function, home, foot massage parlor, hotel, convenience store<br><span class=\"bb_img_ctn\"><img class=\"bb_img\" src=\"https://shared.akamai.steamstatic.com/store_item_assets/steam/apps/2761510/extras/6184b9a3b58dfc38c8598b522f7157f7.avif?t=1750171410\" width=640 height=360 /></span><br>● Boost goodwill, take women from strange, to depraved, be a male porn star yourself, and all the girls can record AVs to share and make money<br><span class=\"bb_img_ctn\"><img class=\"bb_img\" src=\"https://shared.akamai.steamstatic.com/store_item_assets/steam/apps/2761510/extras/4d1808a3ce670327249aed5b5bf44559.avif?t=1750171410\" width=640 height=360 /></span>", "about_the_game": "<h2 class=\"bb_tag\" >Official Community</h2><strong>Join our Discord channel：</strong><br><br><span class=\"bb_img_ctn\"><img class=\"bb_img\" src=\"https://shared.akamai.steamstatic.com/store_item_assets/steam/apps/2761510/extras/723612e7a8783ea223b3b2b5c60dbf0b.avif?t=1750171410\" width=640 height=64 /></span><br><strong>HI, we are Philosophy♂!</strong><br>This is a game that carries our dream of making a simple yet free world-based game.<br>You can just slip in and out of the world, either as a protagonist, or a passerby, and raid at will.<br><span class=\"bb_img_ctn\"><img class=\"bb_img\" src=\"https://shared.akamai.steamstatic.com/store_item_assets/steam/apps/2761510/extras/4e5b51aa912c89179168972429d2f4f1.avif?t=1750171410\" width=640 height=64 /></span><br>The protagonist is an ordinary teenager who is a squatter, but has extraordinary footwork skills, and works part-time to earn pocket money while living under the same roof as his aunt and sister.<br><span class=\"bb_img_ctn\"><img class=\"bb_img\" src=\"https://shared.akamai.steamstatic.com/store_item_assets/steam/apps/2761510/extras/ba69b27f4a3ac73673974c77ae1faa85.avif?t=1750171410\" width=640 height=64 /></span><br><span class=\"bb_img_ctn\"><img class=\"bb_img\" src=\"https://shared.akamai.steamstatic.com/store_item_assets/steam/apps/2761510/extras/13ee59f71dfa8b34f0a895f4bf99ea56.avif?t=1750171410\" width=640 height=360 /></span><br><span class=\"bb_img_ctn\"><img class=\"bb_img\" src=\"https://shared.akamai.steamstatic.com/store_item_assets/steam/apps/2761510/extras/df3311b77c0261dc8975e4012e0a7c06.avif?t=1750171410\" width=640 height=360 /></span><br><span class=\"bb_img_ctn\"><img class=\"bb_img\" src=\"https://shared.akamai.steamstatic.com/store_item_assets/steam/apps/2761510/extras/c806a4c47fffaeae792e169a1b812011.avif?t=1750171410\" width=640 height=64 /></span><br>● The map is free to explore, each building has its own function, home, foot massage parlor, hotel, convenience store<br><span class=\"bb_img_ctn\"><img class=\"bb_img\" src=\"https://shared.akamai.steamstatic.com/store_item_assets/steam/apps/2761510/extras/6184b9a3b58dfc38c8598b522f7157f7.avif?t=1750171410\" width=640 height=360 /></span><br>● Boost goodwill, take women from strange, to depraved, be a male porn star yourself, and all the girls can record AVs to share and make money<br><span class=\"bb_img_ctn\"><img class=\"bb_img\" src=\"https://shared.akamai.steamstatic.com/store_item_assets/steam/apps/2761510/extras/4d1808a3ce670327249aed5b5bf44559.avif?t=1750171410\" width=640 height=360 /></span>", "short_description": "I started a part-time job with my hard-working personality and earned money to buy gifts for my favorite characters.", "supported_languages": "English, Japanese, Simplified Chinese, Traditional Chinese", "header_image": "https://shared.akamai.steamstatic.com/store_item_assets/steam/apps/2761510/header.jpg?t=1750171410", "capsule_image": "https://shared.akamai.steamstatic.com/store_item_assets/steam/apps/2761510/capsule_231x87.jpg?t=1750171410", "capsule_imagev5": "https://shared.akamai.steamstatic.com/store_item_assets/steam/apps/2761510/capsule_184x69.jpg?t=1750171410", "website": null, "pc_requirements": {"minimum": "<strong>Minimum:</strong><br><ul class=\"bb_ul\"><li><strong>OS *:</strong> Windows 7<br></li><li><strong>Processor:</strong> 2 Ghz Dual Core<br></li><li><strong>Memory:</strong> 2 GB RAM<br></li><li><strong>Graphics:</strong> Graphics card supporting DirectX 10.0<br></li><li><strong>Storage:</strong> 4 GB available space</li></ul>", "recommended": "<strong>Recommended:</strong><br><ul class=\"bb_ul\"><li><strong>OS:</strong> Windows 10<br></li><li><strong>Memory:</strong> 2 GB RAM</li></ul>"}, "mac_requirements": [], "linux_requirements": [], "developers": ["philosophy♂"], "publishers": ["monster home"], "price_overview": {"currency": "USD", "initial": 999, "final": 999, "discount_percent": 0, "initial_formatted": "", "final_formatted": "$9.99"}, "categories": [{"id": 2, "description": "Single-player"}, {"id": 62, "description": "Family Sharing"}], "genres": [{"id": "1", "description": "Action"}, {"id": "4", "description": "Casual"}, {"id": "23", "description": "Indie"}, {"id": "3", "description": "RPG"}, {"id": "28", "description": "Simulation"}], "release_date": {"coming_soon": false, "date": "Apr 11, 2024"}}}}, "fetched_at": "2026-04-23T09:04:24Z"}